README.rst
setup.py
udp_test.py
test/test_udp_test.py
udp_test.egg-info/PKG-INFO
udp_test.egg-info/SOURCES.txt
udp_test.egg-info/dependency_links.txt
udp_test.egg-info/entry_points.txt
udp_test.egg-info/requires.txt
udp_test.egg-info/top_level.txt