Metadata-Version: 1.1
Name: udp-test
Version: 0.1.1
Summary: A simple udp server and client for network testing.
Home-page: https://github.com/appstore-zencore/udp-test
Author: zencore
Author-email: dobetter@zencore.cn
License: MIT
Keywords: udp-test
Platform: UNKNOWN
Classifier: Development Status :: 5 - Production/Stable
Classifier: Intended Audience :: Developers
Classifier: Topic :: Software Development :: Libraries :: Python Modules
Classifier: License :: OSI Approved :: MIT License
Classifier: Programming Language :: Python :: 3
Classifier: Programming Language :: Python :: 3 :: Only
Requires: click
